{
    "Objects": [
        {
            "name": "bldr_Misc_Chair_Camp1",
            "pos": [
                11885.900390625,
                140.51800537109376,
                12444.5
            ],
            "ypr": [
                -179.99998474121095,
                0.0,
                0.0
            ]
        },
        {
            "name": "bldr_pultskasou",
            "pos": [
                11885.599609375,
                140.65699768066407,
                12446.099609375
            ],
            "ypr": [
                173.99998474121095,
                0.0,
                0.0
            ]
        },
        {
            "name": "bldr_vending_machine",
            "pos": [
                11879.2998046875,
                141.06100463867188,
                12445.400390625
            ],
            "ypr": [
                -156.99998474121095,
                0.0,
                0.0
            ]
        },
        {
            "name": "bldr_bucket",
            "pos": [
                11884.599609375,
                140.02200317382813,
                12446.099609375
            ],
            "ypr": [
                3.287069797515869,
                0.0,
                0.0
            ]
        },
        {
            "name": "bldr_radio_b",
            "pos": [
                11886.099609375,
                141.02699279785157,
                12446.2001953125
            ],
            "ypr": [
                0.0,
                0.0,
                0.0
            ]
        },
        {
            "name": "Land_Mil_GuardShed",
            "pos": [
                11885.599609375,
                140.81199645996095,
                12445.0
            ],
            "ypr": [
                -9.0,
                0.0,
                0.0
            ]
        },
        {
            "name": "bldr_Sign_EnochMil_Entry_ENPL",
            "pos": [
                11883.400390625,
                140.61700439453126,
                12445.7001953125
            ],
            "ypr": [
                -179.99998474121095,
                0.0,
                0.0
            ]
        },
        {
            "name": "bldr_sign_airport",
            "pos": [
                11883.400390625,
                141.14999389648438,
                12445.5
            ],
            "ypr": [
                -179.99998474121095,
                0.0,
                0.0
            ]
        },
        {
            "name": "bldr_Airfield_LandMark",
            "pos": [
                11886.7001953125,
                140.36500549316407,
                12460.0
            ],
            "ypr": [
                -64.99999237060547,
                0.0,
                0.0
            ]
        },
        {
            "name": "bldr_Airfield_LandMark",
            "pos": [
                11901.900390625,
                140.36500549316407,
                12465.0
            ],
            "ypr": [
                28.0,
                0.0,
                0.0
            ]
        },
        {
            "name": "bldr_Airfield_LandMark",
            "pos": [
                11881.400390625,
                140.36500549316407,
                12474.7001953125
            ],
            "ypr": [
                22.315597534179689,
                0.0,
                0.0
            ]
        },
        {
            "name": "bldr_Airfield_LandMark",
            "pos": [
                11895.900390625,
                140.36500549316407,
                12479.2998046875
            ],
            "ypr": [
                -64.61498260498047,
                0.0,
                0.0
            ]
        },
        {
            "name": "bldr_Airfield_LandMark",
            "pos": [
                11887.5,
                140.36500549316407,
                12480.0
            ],
            "ypr": [
                -106.0,
                0.0,
                0.0
            ]
        },
        {
            "name": "bldr_Airfield_LandMark",
            "pos": [
                11881.0,
                140.36500549316407,
                12466.5
            ],
            "ypr": [
                -21.0,
                0.0,
                0.0
            ]
        },
        {
            "name": "bldr_Airfield_LandMark",
            "pos": [
                11895.7001953125,
                140.36500549316407,
                12459.400390625
            ],
            "ypr": [
                68.0,
                0.0,
                0.0
            ]
        },
        {
            "name": "bldr_Airfield_LandMark",
            "pos": [
                11902.2998046875,
                140.36500549316407,
                12473.599609375
            ],
            "ypr": [
                -23.0,
                0.0,
                0.0
            ]
        },
        {
            "name": "bldr_Airfield_Light_Edge",
            "pos": [
                11894.2001953125,
                140.0449981689453,
                12458.7998046875
            ],
            "ypr": [
                0.0,
                0.0,
                0.0
            ]
        },
        {
            "name": "bldr_Airfield_Light_Edge",
            "pos": [
                11897.0,
                140.0449981689453,
                12459.900390625
            ],
            "ypr": [
                0.0,
                0.0,
                0.0
            ]
        },
        {
            "name": "bldr_Airfield_Light_Edge",
            "pos": [
                11901.2001953125,
                140.0449981689453,
                12463.7001953125
            ],
            "ypr": [
                0.0,
                0.0,
                0.0
            ]
        },
        {
            "name": "bldr_Airfield_Light_Edge",
            "pos": [
                11902.7001953125,
                140.0449981689453,
                12466.2998046875
            ],
            "ypr": [
                0.0,
                0.0,
                0.0
            ]
        },
        {
            "name": "bldr_Airfield_Light_Edge",
            "pos": [
                11902.7998046875,
                140.0449981689453,
                12472.2001953125
            ],
            "ypr": [
                0.0,
                0.0,
                0.0
            ]
        },
        {
            "name": "bldr_Airfield_Light_Edge",
            "pos": [
                11901.7998046875,
                140.0449981689453,
                12475.099609375
            ],
            "ypr": [
                0.0,
                0.0,
                0.0
            ]
        },
        {
            "name": "bldr_Airfield_Light_Edge",
            "pos": [
                11897.2998046875,
                140.0449981689453,
                12478.599609375
            ],
            "ypr": [
                0.0,
                0.0,
                0.0
            ]
        },
        {
            "name": "bldr_Airfield_Light_Edge",
            "pos": [
                11894.5,
                140.0449981689453,
                12480.0
            ],
            "ypr": [
                0.0,
                0.0,
                0.0
            ]
        },
        {
            "name": "bldr_Airfield_Light_Edge",
            "pos": [
                11888.900390625,
                140.0449981689453,
                12480.599609375
            ],
            "ypr": [
                0.0,
                0.0,
                0.0
            ]
        },
        {
            "name": "bldr_Airfield_Light_Edge",
            "pos": [
                11886.0,
                140.0449981689453,
                12479.7001953125
            ],
            "ypr": [
                0.0,
                0.0,
                0.0
            ]
        },
        {
            "name": "bldr_Airfield_Light_Edge",
            "pos": [
                11882.099609375,
                140.0449981689453,
                12476.2001953125
            ],
            "ypr": [
                0.0,
                0.0,
                0.0
            ]
        },
        {
            "name": "bldr_Airfield_Light_Edge",
            "pos": [
                11880.7998046875,
                140.0449981689453,
                12473.400390625
            ],
            "ypr": [
                0.0,
                0.0,
                0.0
            ]
        },
        {
            "name": "bldr_Airfield_Light_Edge",
            "pos": [
                11880.5,
                140.0449981689453,
                12468.0
            ],
            "ypr": [
                0.0,
                0.0,
                0.0
            ]
        },
        {
            "name": "bldr_Airfield_Light_Edge",
            "pos": [
                11881.5,
                140.0449981689453,
                12464.900390625
            ],
            "ypr": [
                0.0,
                0.0,
                0.0
            ]
        },
        {
            "name": "bldr_Airfield_Light_Edge",
            "pos": [
                11885.2001953125,
                140.0449981689453,
                12460.7998046875
            ],
            "ypr": [
                0.0,
                0.0,
                0.0
            ]
        },
        {
            "name": "bldr_Airfield_Light_Edge",
            "pos": [
                11888.0,
                140.0449981689453,
                12459.2998046875
            ],
            "ypr": [
                0.0,
                0.0,
                0.0
            ]
        },
        {
            "name": "bldr_Airfield_Lamp",
            "pos": [
                11866.7998046875,
                152.41900634765626,
                12455.400390625
            ],
            "ypr": [
                18.0,
                0.0,
                0.0
            ]
        },
        {
            "name": "Wreck_UH1Y",
            "pos": [
                11902.900390625,
                141.8800048828125,
                12451.7001953125
            ],
            "ypr": [
                61.99999237060547,
                -0.07635220140218735,
                0.07635240256786347
            ]
        },
        {
            "name": "bldr_mil_camonet_tent2",
            "pos": [
                4162.419921875,
                385.4639892578125,
                11753.0
            ],
            "ypr": [
                -28.99919891357422,
                1.8472999334335328,
                -0.3056409955024719
            ]
        },
        {
            "name": "bldr_Wall_Barricade1_10",
            "pos": [
                4164.6298828125,
                383.6719970703125,
                11749.2001953125
            ],
            "ypr": [
                -32.99980163574219,
                -0.15270398557186128,
                -0.07646919786930084
            ]
        },
        {
            "name": "bldr_sign_nofishing",
            "pos": [
                4155.4501953125,
                384.072998046875,
                11753.5
            ],
            "ypr": [
                0.0,
                0.0,
                -0.30564001202583315
            ]
        },
        {
            "name": "bldr_sign_camp_scholar",
            "pos": [
                4160.490234375,
                383.66400146484377,
                11745.7001953125
            ],
            "ypr": [
                -123.99998474121094,
                0.0,
                -0.4583379030227661
            ]
        },
        {
            "name": "Barrel_Red",
            "pos": [
                4160.4501953125,
                383.635009765625,
                11752.0
            ],
            "ypr": [
                0.0,
                0.0,
                0.0
            ]
        },
        {
            "name": "bldr_wreck_powgen",
            "pos": [
                4158.1298828125,
                384.2699890136719,
                11755.900390625
            ],
            "ypr": [
                48.00019836425781,
                0.0,
                0.0
            ]
        },
        {
            "name": "Flag_Chedaki",
            "pos": [
                4155.10009765625,
                383.6510009765625,
                11764.099609375
            ],
            "ypr": [
                0.0,
                0.0,
                0.0
            ]
        },
        {
            "name": "bldr_sign_city_chernogorsk",
            "pos": [
                4158.14990234375,
                385.7659912109375,
                11740.400390625
            ],
            "ypr": [
                -138.00100708007813,
                0.07645250111818314,
                -0.8403999209403992
            ]
        },
        {
            "name": "Wreck_Mi8",
            "pos": [
                4150.93994140625,
                384.56500244140627,
                11733.400390625
            ],
            "ypr": [
                73.82711791992188,
                3.50115966796875,
                -2.829549789428711
            ]
        },
        {
            "name": "bldr_wreck_decal_small1",
            "pos": [
                4155.31982421875,
                383.64801025390627,
                11753.7001953125
            ],
            "ypr": [
                97.99999237060547,
                -0.2100829780101776,
                -0.6108130216598511
            ]
        },
        {
            "name": "bldr_wreck_decal_small1",
            "pos": [
                4159.5400390625,
                383.6650085449219,
                11755.400390625
            ],
            "ypr": [
                179.99998474121095,
                0.00037008896470069885,
                -0.6130610108375549
            ]
        }
    ]
}